fixshell/__init__.py
fixshell/__main__.py
fixshell/authorized_client.py
fixshell/benchmark.py
fixshell/promptsession.py
fixshell/protected_files.py
fixshell/shell.py
fixinventoryshell-4.2.0.dist-info/METADATA
fixinventoryshell-4.2.0.dist-info/WHEEL
fixinventoryshell-4.2.0.dist-info/entry_points.txt
fixinventoryshell-4.2.0.dist-info/top_level.txt
fixinventoryshell-4.2.0.dist-info/RECORD
