Metadata-Version: 2.1
Name: fixinventoryshell
Version: 4.2.0
Summary: Commandline interpreter to interact with Fix Inventory.
Author: Some Engineering Inc.
License: AGPLv3
Project-URL: Documentation, https://inventory.fix.security
Project-URL: Source, https://github.com/someengineering/fix/tree/main/fixshell
Keywords: cloud security
Classifier: Development Status :: 5 - Production/Stable
Classifier: Intended Audience :: System Administrators
Classifier: Intended Audience :: Information Technology
Classifier: License :: OSI Approved :: GNU Affero General Public License v3 or later (AGPLv3+)
Classifier: Programming Language :: Python :: 3.12
Classifier: Operating System :: POSIX :: Linux
Classifier: Operating System :: Unix
Classifier: Environment :: Console
Classifier: Natural Language :: English
Classifier: Topic :: Security
Classifier: Topic :: Utilities
Requires-Python: >=3.12
Requires-Dist: fixinventorylib==4.2.0
Requires-Dist: prompt-toolkit
Requires-Dist: rich
Requires-Dist: fixinventoryclient
Requires-Dist: aiohttp[speedups]
